python_for_fluss-0.1.0.dist-info/RECORD
python_for_fluss-0.1.0.dist-info/WHEEL
python_for_fluss-0.1.0.dist-info/METADATA
fluss_python/__init__.pyi
fluss_python/__init__.py
fluss_python/py.typed
fluss_python/fluss_python.cpython-39-darwin.so
