Metadata-Version: 2.4
Name: python-for-fluss
Version: 0.1.1
Classifier: Programming Language :: Rust
Classifier: Programming Language :: Python :: Implementation :: CPython
Requires-Dist: pandas>=2.3.1
Requires-Dist: pyarrow>=10.0.0
Requires-Dist: mypy>=1.17.1 ; extra == 'dev'
Requires-Dist: pytest>=8.3.5 ; extra == 'dev'
Requires-Dist: pytest-asyncio>=0.25.3 ; extra == 'dev'
Requires-Dist: ruff>=0.9.10 ; extra == 'dev'
Requires-Dist: maturin>=1.8.2 ; extra == 'dev'
Requires-Dist: pdoc>=15.0.4 ; extra == 'docs'
Requires-Dist: tqdm>=4.67.1 ; extra == 'extra'
Requires-Dist: duckdb>=0.9.0 ; extra == 'extra'
Requires-Dist: pylance>=0.33.0 ; extra == 'extra'
Provides-Extra: dev
Provides-Extra: docs
Provides-Extra: extra
Summary: Python bindings for Fluss
Author: Fluss Team
License: Apache-2.0
Requires-Python: >=3.9
Project-URL: Repository, https://github.com/apache/fluss-rust
